whistling/__init__.py
whistling/abstract_reporter.py
whistling/ecx.py
whistling/gsb.py
whistling/netcraft.py
whistling/urlscan.py
whistling-1.0.0.dist-info/LICENSE
whistling-1.0.0.dist-info/METADATA
whistling-1.0.0.dist-info/WHEEL
whistling-1.0.0.dist-info/RECORD
